desktopassistant/__init__.py
desktopassistant/desktopassistant.py
desktopassistant-1.0.3.dist-info/METADATA
desktopassistant-1.0.3.dist-info/WHEEL
desktopassistant-1.0.3.dist-info/top_level.txt
desktopassistant-1.0.3.dist-info/RECORD
