Metadata-Version: 2.1
Name: desktopassistant
Version: 1.0.3
Summary: Desktop Assistant which takes commands as speech & convert to text. Speaks the text provided. Wishes the User as per the Hour of the day. It also can send E-Mails.
Home-page: UNKNOWN
Author: Akshat Bhatter (Developer_Akshat)
Author-email: <bhatterakshat4@gmail.com>
License: UNKNOWN
Keywords: python,AI,Desktop Assistant,Assistant,Virtual Assistant
Platform: UNKNOWN
Classifier: Development Status :: 3 - Alpha
Classifier: Intended Audience :: Developers
Classifier: Programming Language :: Python :: 3
Classifier: Operating System :: Microsoft :: Windows
Requires-Dist: comtypes
Requires-Dist: pyttsx3
Requires-Dist: speechRecognition
